Metadata-Version: 1.2
Name: slmpy
Version: 0.3.1
Summary: Smart local moving (SLM) community detection in Python/C++
Home-page: https://github.com/iosonofabio/slmpy
Author: Fabio Zanini
Author-email: fabio.zanini@stanford.edu
Maintainer: Fabio Zanini
Maintainer-email: fabio.zanini@fastmail.fm
License: MIT
Platform: UNKNOWN
Classifier: Topic :: Scientific/Engineering :: Bio-Informatics
Classifier: Intended Audience :: Developers
Classifier: Intended Audience :: Science/Research
Classifier: License :: OSI Approved :: MIT License
Classifier: Operating System :: POSIX
Classifier: Programming Language :: Python
